ciatools/__init__.py
ciatools/callbox_control.py
ciatools/flash_tools.py
ciatools/logger.py
ciatools/py.typed
ciatools/uart.py
ciatools-0.6.0.dist-info/WHEEL
ciatools-0.6.0.dist-info/METADATA
ciatools-0.6.0.dist-info/RECORD
