Metadata-Version: 2.3
Name: ciatools
Version: 0.6.0
Summary: Utilities
Author: Jorgen Kvalvaag
Author-email: Jorgen Kvalvaag <jorgen.kvalvaag@nordicsemi.no>
Requires-Dist: pyserial>=3.5
Requires-Dist: termcolor>=3.1.0
Requires-Dist: pyocd>=0.39
Requires-Dist: websockets
Requires-Python: >=3.12
